nvidia_tao_core/__init__.py
nvidia_tao_core/api_utils/__init__.py
nvidia_tao_core/api_utils/common_utils.py
nvidia_tao_core/api_utils/dataclass2json_converter.py
nvidia_tao_core/api_utils/json_schema_validation.py
nvidia_tao_core/api_utils/microservice_utils.py
nvidia_tao_core/api_utils/module_utils.py
nvidia_tao_core/api_utils/ngc_utils.py
nvidia_tao_core/api_utils/entrypoint_mimicker/__init__.py
nvidia_tao_core/api_utils/entrypoint_mimicker/vlm_entrypoint.py
nvidia_tao_core/callbacks/__init__.py
nvidia_tao_core/callbacks/transformers_status_callback.py
nvidia_tao_core/config/__init__.py
nvidia_tao_core/config/action_recognition/__init__.py
nvidia_tao_core/config/action_recognition/default_config.py
nvidia_tao_core/config/analytics/__init__.py
nvidia_tao_core/config/analytics/default_config.py
nvidia_tao_core/config/annotations/__init__.py
nvidia_tao_core/config/annotations/default_config.py
nvidia_tao_core/config/annotations/merge_config.py
nvidia_tao_core/config/annotations/slice_config.py
nvidia_tao_core/config/augmentation/__init__.py
nvidia_tao_core/config/augmentation/default_config.py
nvidia_tao_core/config/auto_label/__init__.py
nvidia_tao_core/config/auto_label/default_config.py
nvidia_tao_core/config/bevfusion/__init__.py
nvidia_tao_core/config/bevfusion/dataset.py
nvidia_tao_core/config/bevfusion/default_config.py
nvidia_tao_core/config/bevfusion/model.py
nvidia_tao_core/config/bevfusion/train.py
nvidia_tao_core/config/centerpose/__init__.py
nvidia_tao_core/config/centerpose/dataset.py
nvidia_tao_core/config/centerpose/default_config.py
nvidia_tao_core/config/centerpose/deploy.py
nvidia_tao_core/config/centerpose/model.py
nvidia_tao_core/config/centerpose/train.py
nvidia_tao_core/config/classification_pyt/__init__.py
nvidia_tao_core/config/classification_pyt/default_config.py
nvidia_tao_core/config/classification_pyt/model_params_mapping.py
nvidia_tao_core/config/classification_pyt_mmlab/__init__.py
nvidia_tao_core-6.25.11.dist-info/licenses/LICENSE
nvidia_tao_core-6.25.11.dist-info/METADATA
nvidia_tao_core-6.25.11.dist-info/WHEEL
nvidia_tao_core-6.25.11.dist-info/entry_points.txt
nvidia_tao_core-6.25.11.dist-info/top_level.txt
nvidia_tao_core-6.25.11.dist-info/RECORD
