Metadata-Version: 2.4
Name: nvidia-tao-core
Version: 6.25.11
Summary: NVIDIA's package for core modules common across TAO Toolkit DNNs.
Author: NVIDIA Corporation
License: NVIDIA Proprietary Software
Keywords: nvidia,tao,core
Classifier: Environment :: Console
Classifier: License :: Other/Proprietary License
Classifier: Natural Language :: English
Classifier: Operating System :: POSIX :: Linux
Classifier: Programming Language :: Python
Classifier: Topic :: Scientific/Engineering :: Artificial Intelligence
License-File: LICENSE
Requires-Dist: apache-libcloud
Requires-Dist: apispec==6.8.2
Requires-Dist: apispec-oneofschema==3.0.2
Requires-Dist: apispec-webframeworks==1.2.0
Requires-Dist: cryptography>43.0.1
Requires-Dist: dicomweb-client==0.60.0
Requires-Dist: docker
Requires-Dist: filelock
Requires-Dist: flake8
Requires-Dist: Flask==3.1.1
Requires-Dist: Flask-Limiter==3.12
Requires-Dist: Flask-WTF>=1.1.0
Requires-Dist: grpcio==1.67.1
Requires-Dist: huggingface_hub
Requires-Dist: jsonschema
Requires-Dist: kubernetes==32.0.1
Requires-Dist: marshmallow==3.26.1
Requires-Dist: marshmallow-enum==1.5.1
Requires-Dist: marshmallow-oneofschema==3.2.0
Requires-Dist: ngcsdk==3.151.0
Requires-Dist: numpy
Requires-Dist: omegaconf==2.3.0
Requires-Dist: orjson
Requires-Dist: packaging
Requires-Dist: pandas
Requires-Dist: pyarmor
Requires-Dist: pycryptodome==3.23.0
Requires-Dist: pycocotools
Requires-Dist: pydicom==3.0.1
Requires-Dist: pydocstyle
Requires-Dist: pymongo==4.13.0
Requires-Dist: pylint
Requires-Dist: pynvml==12.0.0
Requires-Dist: PyJWT
Requires-Dist: PyYAML
Requires-Dist: requests==2.32.3
Requires-Dist: requests_toolbelt==1.0.0
Requires-Dist: ruamel.yaml==0.18.12
Requires-Dist: s3fs
Requires-Dist: scikit-learn>=1.3.0
Requires-Dist: scipy
Requires-Dist: setuptools==78.1.1
Requires-Dist: six==1.16.0
Requires-Dist: timeloop==1.0.2
Requires-Dist: toml
Requires-Dist: torchao==0.11.0
Requires-Dist: transformers
Requires-Dist: tritonclient[all]
Requires-Dist: uWSGI
Requires-Dist: validators==0.35.0
Requires-Dist: Werkzeug==3.1.3
Dynamic: author
Dynamic: classifier
Dynamic: keywords
Dynamic: license
Dynamic: license-file
Dynamic: requires-dist
Dynamic: summary
